checknet/__init__.py
checknet-0.1.0.dist-info/METADATA
checknet-0.1.0.dist-info/WHEEL
checknet-0.1.0.dist-info/top_level.txt
checknet-0.1.0.dist-info/RECORD
